{
    "$schema": "https://schema.management.azure.com/schemas/2019-04-01/deploymentParameters.json#",
    "contentVersion": "1.0.0.0",
    "parameters": {
      "env": {
        "value": "prd"
      },
      "resourceNameSuffix": {
        "value": "0411"
      },
      "storageAccountName": {
        "value": "stazshared0411prd"
      },
      "sharedResourceGroupName": {
        "value": "azshared-prd-rg"
      },
      "platformResourceGroupName": {
        "value": "azplatform-rg"
      },
      "keyVaultName": {
        "value": "kv-azshared-0411-prd"
      },
      "logAnalyticsWorkspaceName": {
        "value": "lw-azplatform-0411"
      }
    }
  }